wtas/__init__.py
wtas/functions.py
wtas/main.py
wtas/operators.py
wtas/tests/__init__.py
wtas/tests/main_test.py
wta-0.1.0.dist-info/LICENSE
wta-0.1.0.dist-info/METADATA
wta-0.1.0.dist-info/WHEEL
wta-0.1.0.dist-info/top_level.txt
wta-0.1.0.dist-info/RECORD
