Metadata-Version: 2.1
Name: wta
Version: 0.1.0
Summary: UNKNOWN
Home-page: UNKNOWN
Author: PunchyArchy
Author-email: ksmdrmvscthny@gmail.com
License: UNKNOWN
Platform: UNKNOWN
License-File: LICENSE
Requires-Dist: psycopg2
Requires-Dist: ar-one-qdk
